retina/__init__.py
retina/core.py
retina/optic/__init__.py
retina/optic/cortex.py
vitreous-0.0.1.dist-info/METADATA
vitreous-0.0.1.dist-info/WHEEL
vitreous-0.0.1.dist-info/top_level.txt
vitreous-0.0.1.dist-info/RECORD
