Metadata-Version: 2.1
Name: vitreous
Version: 0.0.1
Requires-Dist: pillow>=11.0.0
Requires-Dist: pytesseract>=0.3.13
